setup.py
pandas_db/__init__.py
pandas_db/table_creator.py
table_creator.egg-info/PKG-INFO
table_creator.egg-info/SOURCES.txt
table_creator.egg-info/dependency_links.txt
table_creator.egg-info/requires.txt
table_creator.egg-info/top_level.txt