Metadata-Version: 1.0
Name: table-creator
Version: 0.0.5
Summary: Package to create tables in various sgbd
Home-page: UNKNOWN
Author: laurent.erreca
Author-email: erreca.laurent@gmail.com
License: UNKNOWN
Platform: UNKNOWN
